Workbook

Sheet Cover
A1: Aerospace Manufacturer, Inc.
A2: FX Transaction Hedge Model — EUR 20,000,000 Receivable
A3: FIN-321 International Finance & Securities — Stage 3 AI-Assisted Build
A5: Prepared by | B5: Joy Scofield
A6: Date | B6: 2026-07-30
A7: Scenario | B7: #20 — Aerospace Manufacturer (Scenario 4)
A8: Exposure | B8: EUR 20,000,000 receivable, 365-day settlement
A9: Companion Spec | B9: docs/specs/2026-07-30-Scofield-aerospace-spec.md
A11: Data Provenance
A12: All market inputs (spot, rates, strikes) are INDICATIVE placeholders, sourced and
A13: timestamped as of 2026-07-30 (see Inputs tab, column E). They will be replaced with
A14: live, verified market data at Stage 4. The forward rate and option premiums are
A15: course-assigned (Scenario 4) and are not derived from the spot/rate inputs — see
A16: Notes & Assumptions tab for the resulting parity-check gap.

Sheet Legend
A1: Legend / Key
A3: Color Convention (applied throughout this workbook)
A4: Yellow fill | B4: Input — raw market/contract data, hardcoded
A5: Blue text | B5: Assumption — analyst-set scenario knob
A6: Green text | B6: Formula — computed value, references named ranges
A7: Gray fill | B7: Output — headline result reported to the CFO
A10: Named Range Glossary
A11: FC_AMT | B11: Foreign-currency receivable (EUR)
A12: S0_in | B12: Spot rate at inception (USD per EUR)
A13: F0_in | B13: Forward rate to settlement (USD per EUR)
A14: R_USD | B14: USD interest rate to settlement (annual %)
A15: R_FC | B15: EUR interest rate to settlement (annual %)
A16: T_DAYS | B16: Days to settlement
A17: BASIS | B17: Day-count denominator, both legs (ACT/360)
A18: K_PUT | B18: Put option strike (USD per EUR)
A19: K_CALL | B19: Call option strike (USD per EUR, reference)
A20: PREM_PUT | B20: Put premium, USD per 1 EUR
A21: PREM_CALL | B21: Call premium, USD per 1 EUR (reference)
A22: DF_USD | B22: USD accumulation factor to settlement (derived)
... A26: STEP_FRAC | B26: Sensitivity grid step size (1%)

Sheet Inputs
A1: Inputs — Named Range Contract
A3: Named Range | B3: Description | C3: Value | D3: Unit | E3: Source
A4: FC_AMT | B4: Foreign-currency receivable | C4: 20000000 | D4: EUR | E4: Contract terms (fixed, not market-sourced)
A5: S0_in | B5: Spot rate at inception | C5: 1.1526 | D5: USD per EUR | E5: EURUSD spot, Investing.com, accessed 2026-07-30 — INDICATIVE
A6: F0_in | B6: Forward rate to settlement | C6: 1.0935 | D6: USD per EUR | E6: Course-assigned (Scenario 4, Aerospace) — INDICATIVE
A7: R_USD | B7: USD interest rate to settlement | C7: 0.0363 | D7: Annual %, ACT/360 | E7: Effective Fed funds rate, accessed 2026-07-30 — INDICATIVE
A8: R_FC | B8: EUR interest rate to settlement | C8: 0.0225 | D8: Annual %, ACT/360 | E8: ECB deposit facility rate (eff. 17 Jun 2026), accessed 2026-07-30 — INDICATIVE
A9: T_DAYS | B9: Days to settlement | C9: 365 | D9: Days | E9: Contract terms (fixed)
A10: BASIS | B10: Day-count denominator, both legs | C10: 360 | D10: Days | E10: ACT/360 — per Stage 2 assignment's worked formula
A11: K_PUT | B11: Put option strike | C11: 1.1526 | D11: USD per EUR | E11: Set at spot (ATM) per course guidance — INDICATIVE
A12: K_CALL | B12: Call option strike (reference) | C12: 1.1526 | D12: USD per EUR | E12: Set at spot (ATM), reference only — INDICATIVE
A13: PREM_PUT | B13: Put premium, USD per 1 EUR | C13: 0.019 | D13: USD | E13: Course-assigned (Scenario 4) — INDICATIVE
A14: PREM_CALL | B14: Call premium, USD per 1 EUR (reference) | C14: 0.024 | D14: USD | E14: Course-assigned (Scenario 4) — INDICATIVE
A15: STEP_FRAC | B15: Sensitivity grid step size | C15: 0.01 | D15: Fraction | E15: Assignment spec: 1% steps
A17: Derived Values
A18: Named Range | B18: Description | C18: Value | D18: Formula (named-range notation)
A19: DF_USD | B19: USD accumulation factor to settlement | C19: =1+R_USD*T_DAYS/BASIS -> 1.0368042 | D19: 1 + R_USD × T_DAYS / BASIS
A20: DF_FC | B20: EUR accumulation factor to settlement | C20: =1+R_FC*T_DAYS/BASIS -> 1.0228125 | D20: 1 + R_FC × T_DAYS / BASIS
A21: FV_PREM_PUT | B21: Future value of put premium at settlement | C21: =-PREM_PUT*FC_AMT*DF_USD -> -393985.58 | D21: −PREM_PUT × FC_AMT × DF_USD
A22: FV_PREM_CALL | B22: Future value of call premium at settlement (reference) | C22: =-PREM_CALL*FC_AMT*DF_USD -> -497666 | D22: −PREM_CALL × FC_AMT × DF_USD

Sheet Forward
A1: Forward Hedge
A2: Locks in today's forward rate for delivery at settlement.
A4: USD Proceeds (locked) | B4: =FC_AMT*F0_in -> 21870000 | C4: Formula: FC_AMT x F0_in
A6: Note: This value is invariant across the S_T sensitivity grid — the forward
A7: hedge removes all exposure to future spot movements.

Sheet MoneyMarket
A1: Money Market Hedge
A2: Replicates the forward via borrow / convert / invest — three explicit steps.
A4: Step 1 — Borrow EUR today
A5: Borrow (EUR) | B5: =FC_AMT/DF_FC -> 19553926 | C5: Formula: FC_AMT / DF_FC
A7: Step 2 — Convert at spot
A8: USD Now | B8: =B5*S0_in -> 22537855 | C8: Formula: Borrow x S0_in
A10: Step 3 — Invest in USD to settlement
A11: USD Proceeds (Money Market) | B11: =B8*DF_USD -> 23367342 | C11: Formula: USD Now x DF_USD
A13: Parity Check
A14: F_implied (from S0_in, R_USD, R_FC) | B14: =S0_in*DF_USD/DF_FC -> 1.1683671
A15: F0_in (given, course-assigned) | B15: =F0_in -> 1.0935
A16: Difference (F_implied − F0_in) | B16: =B14-B15 -> 0.074867108
A17: Parity check (tol. 0.01) | B17: =IF(ABS(B16)<0.01,"PASS","GAP — expected, see Notes tab (F0_in is course-assigned, not market-derived)") -> GAP — expected, see Notes tab (F0_in is course-assigned, not market-derived)

Sheet Options
A1: Options Hedge — Put (primary) and Call (reference)
A2: Put is the primary hedge for this receivable (protective floor). Call payoff shown for reference
A3: as the payable-side analog — not the recommended hedge for this exposure.
A5: n | B5: S_T | C5: No Hedge | D5: Put Proceeds | E5: Call Proceeds (ref.)
A6: -5 | B6: =S0_in*(1+A6*STEP_FRAC) -> 1.09497 | C6: =B6*FC_AMT -> 21899400 | D6: =MAX(B6,K_PUT)*FC_AMT+FV_PREM_PUT -> 22658014 | E6: =MIN(B6,K_CALL)*FC_AMT+FV_PREM_CALL -> 21401734
A7: -4 | B7: =S0_in*(1+A7*STEP_FRAC) -> 1.106496 | C7: =B7*FC_AMT -> 22129920 | D7: =MAX(B7,K_PUT)*FC_AMT+FV_PREM_PUT -> 22658014 | E7: =MIN(B7,K_CALL)*FC_AMT+FV_PREM_CALL -> 21632254
A8: -3 | B8: =S0_in*(1+A8*STEP_FRAC) -> 1.118022 | C8: =B8*FC_AMT -> 22360440 | D8: =MAX(B8,K_PUT)*FC_AMT+FV_PREM_PUT -> 22658014 | E8: =MIN(B8,K_CALL)*FC_AMT+FV_PREM_CALL -> 21862774
A9: -2 | B9: =S0_in*(1+A9*STEP_FRAC) -> 1.129548 | C9: =B9*FC_AMT -> 22590960 | D9: =MAX(B9,K_PUT)*FC_AMT+FV_PREM_PUT -> 22658014 | E9: =MIN(B9,K_CALL)*FC_AMT+FV_PREM_CALL -> 22093294
A10: -1 | B10: =S0_in*(1+A10*STEP_FRAC) -> 1.141074 | C10: =B10*FC_AMT -> 22821480 | D10: =MAX(B10,K_PUT)*FC_AMT+FV_PREM_PUT -> 22658014 | E10: =MIN(B10,K_CALL)*FC_AMT+FV_PREM_CALL -> 22323814
A11: 0 | B11: =S0_in*(1+A11*STEP_FRAC) -> 1.1526 | C11: =B11*FC_AMT -> 23052000 | D11: =MAX(B11,K_PUT)*FC_AMT+FV_PREM_PUT -> 22658014 | E11: =MIN(B11,K_CALL)*FC_AMT+FV_PREM_CALL -> 22554334
A12: 1 | B12: =S0_in*(1+A12*STEP_FRAC) -> 1.164126 | C12: =B12*FC_AMT -> 23282520 | D12: =MAX(B12,K_PUT)*FC_AMT+FV_PREM_PUT -> 22888534 | E12: =MIN(B12,K_CALL)*FC_AMT+FV_PREM_CALL -> 22554334
A13: 2 | B13: =S0_in*(1+A13*STEP_FRAC) -> 1.175652 | C13: =B13*FC_AMT -> 23513040 | D13: =MAX(B13,K_PUT)*FC_AMT+FV_PREM_PUT -> 23119054 | E13: =MIN(B13,K_CALL)*FC_AMT+FV_PREM_CALL -> 22554334
A14: 3 | B14: =S0_in*(1+A14*STEP_FRAC) -> 1.187178 | C14: =B14*FC_AMT -> 23743560 | D14: =MAX(B14,K_PUT)*FC_AMT+FV_PREM_PUT -> 23349574 | E14: =MIN(B14,K_CALL)*FC_AMT+FV_PREM_CALL -> 22554334
A15: 4 | B15: =S0_in*(1+A15*STEP_FRAC) -> 1.198704 | C15: =B15*FC_AMT -> 23974080 | D15: =MAX(B15,K_PUT)*FC_AMT+FV_PREM_PUT -> 23580094 | E15: =MIN(B15,K_CALL)*FC_AMT+FV_PREM_CALL -> 22554334
A16: 5 | B16: =S0_in*(1+A16*STEP_FRAC) -> 1.21023 | C16: =B16*FC_AMT -> 24204600 | D16: =MAX(B16,K_PUT)*FC_AMT+FV_PREM_PUT -> 23810614 | E16: =MIN(B16,K_CALL)*FC_AMT+FV_PREM_CALL -> 22554334
A18: USD_FLOOR_PUT (worst-case put outcome on grid) | D18: =MIN(D6:D16) -> 22658014

Sheet Sensitivity
A1: Sensitivity Analysis
A2: S_T grid: S0_in × (1 ± 5%) in 1% steps (11 rows).
A4: Strategy Summary (base case, S_T = S0_in)
A5: USD_BASE_NoHedge | B5: =S0_in*FC_AMT -> 23052000
A6: USD_FWD (Forward) | B6: =Forward!B4 -> 21870000
A7: USD_MM (Money Market) | B7: =MoneyMarket!B11 -> 23367342
A8: USD_BASE_PUT (Option, at S0_in) | B8: =MAX(S0_in,K_PUT)*FC_AMT+FV_PREM_PUT -> 22658014
A9: USD_FLOOR_PUT (Option, worst case) | B9: =Options!D18 -> 22658014
A12: n | B12: S_T | C12: No Hedge | D12: Forward | E12: Money Market | F12: Option (Put) | G12: Profit vs No Hedge: Fwd | H12: Profit vs No Hedge: MM | I12: Profit vs No Hedge: Put | J12: Best Active Hedge
A13: -5 | B13: =S0_in*(1+A13*STEP_FRAC) -> 1.09497 | C13: =B13*FC_AMT -> 21899400 | D13: =Forward!$B$4 -> 21870000 | E13: =MoneyMarket!$B$11 -> 23367342 | F13: =MAX(B13,K_PUT)*FC_AMT+FV_PREM_PUT -> 22658014 | G13: =D13-C13 -> -29400 | H13: =E13-C13 -> 1467942.2 | I13: =F13-C13 -> 758614.42 | J13: =IF(AND(D13>=E13,D13>=F13),"Forward",IF(E13>=F13,"Money Market","Put Option")) -> Money Market
A14: -4 | B14: =S0_in*(1+A14*STEP_FRAC) -> 1.106496 | C14: =B14*FC_AMT -> 22129920 | D14: =Forward!$B$4 -> 21870000 | E14: =MoneyMarket!$B$11 -> 23367342 | F14: =MAX(B14,K_PUT)*FC_AMT+FV_PREM_PUT -> 22658014 | G14: =D14-C14 -> -259920 | H14: =E14-C14 -> 1237422.2 | I14: =F14-C14 -> 528094.42 | J14: =IF(AND(D14>=E14,D14>=F14),"Forward",IF(E14>=F14,"Money Market","Put Option")) -> Money Market
A15: -3 | B15: =S0_in*(1+A15*STEP_FRAC) -> 1.118022 | C15: =B15*FC_AMT -> 22360440 | D15: =Forward!$B$4 -> 21870000 | E15: =MoneyMarket!$B$11 -> 23367342 | F15: =MAX(B15,K_PUT)*FC_AMT+FV_PREM_PUT -> 22658014 | G15: =D15-C15 -> -490440 | H15: =E15-C15 -> 1006902.2 | I15: =F15-C15 -> 297574.42 | J15: =IF(AND(D15>=E15,D15>=F15),"Forward",IF(E15>=F15,"Money Market","Put Option")) -> Money Market
A16: -2 | B16: =S0_in*(1+A16*STEP_FRAC) -> 1.129548 | C16: =B16*FC_AMT -> 22590960 | D16: =Forward!$B$4 -> 21870000 | E16: =MoneyMarket!$B$11 -> 23367342 | F16: =MAX(B16,K_PUT)*FC_AMT+FV_PREM_PUT -> 22658014 | G16: =D16-C16 -> -720960 | H16: =E16-C16 -> 776382.16 | I16: =F16-C16 -> 67054.417 | J16: =IF(AND(D16>=E16,D16>=F16),"Forward",IF(E16>=F16,"Money Market","Put Option")) -> Money Market
A17: -1 | B17: =S0_in*(1+A17*STEP_FRAC) -> 1.141074 | C17: =B17*FC_AMT -> 22821480 | D17: =Forward!$B$4 -> 21870000 | E17: =MoneyMarket!$B$11 -> 23367342 | F17: =MAX(B17,K_PUT)*FC_AMT+FV_PREM_PUT -> 22658014 | G17: =D17-C17 -> -951480 | H17: =E17-C17 -> 545862.16 | I17: =F17-C17 -> -163465.58 | J17: =IF(AND(D17>=E17,D17>=F17),"Forward",IF(E17>=F17,"Money Market","Put Option")) -> Money Market
A18: 0 | B18: =S0_in*(1+A18*STEP_FRAC) -> 1.1526 | C18: =B18*FC_AMT -> 23052000 | D18: =Forward!$B$4 -> 21870000 | E18: =MoneyMarket!$B$11 -> 23367342 | F18: =MAX(B18,K_PUT)*FC_AMT+FV_PREM_PUT -> 22658014 | G18: =D18-C18 -> -1182000 | H18: =E18-C18 -> 315342.16 | I18: =F18-C18 -> -393985.58 | J18: =IF(AND(D18>=E18,D18>=F18),"Forward",IF(E18>=F18,"Money Market","Put Option")) -> Money Market
A19: 1 | B19: =S0_in*(1+A19*STEP_FRAC) -> 1.164126 | C19: =B19*FC_AMT -> 23282520 | D19: =Forward!$B$4 -> 21870000 | E19: =MoneyMarket!$B$11 -> 23367342 | F19: =MAX(B19,K_PUT)*FC_AMT+FV_PREM_PUT -> 22888534 | G19: =D19-C19 -> -1412520 | H19: =E19-C19 -> 84822.157 | I19: =F19-C19 -> -393985.58 | J19: =IF(AND(D19>=E19,D19>=F19),"Forward",IF(E19>=F19,"Money Market","Put Option")) -> Money Market
A20: 2 | B20: =S0_in*(1+A20*STEP_FRAC) -> 1.175652 | C20: =B20*FC_AMT -> 23513040 | D20: =Forward!$B$4 -> 21870000 | E20: =MoneyMarket!$B$11 -> 23367342 | F20: =MAX(B20,K_PUT)*FC_AMT+FV_PREM_PUT -> 23119054 | G20: =D20-C20 -> -1643040 | H20: =E20-C20 -> -145697.84 | I20: =F20-C20 -> -393985.58 | J20: =IF(AND(D20>=E20,D20>=F20),"Forward",IF(E20>=F20,"Money Market","Put Option")) -> Money Market
A21: 3 | B21: =S0_in*(1+A21*STEP_FRAC) -> 1.187178 | C21: =B21*FC_AMT -> 23743560 | D21: =Forward!$B$4 -> 21870000 | E21: =MoneyMarket!$B$11 -> 23367342 | F21: =MAX(B21,K_PUT)*FC_AMT+FV_PREM_PUT -> 23349574 | G21: =D21-C21 -> -1873560 | H21: =E21-C21 -> -376217.84 | I21: =F21-C21 -> -393985.58 | J21: =IF(AND(D21>=E21,D21>=F21),"Forward",IF(E21>=F21,"Money Market","Put Option")) -> Money Market
A22: 4 | B22: =S0_in*(1+A22*STEP_FRAC) -> 1.198704 | C22: =B22*FC_AMT -> 23974080 | D22: =Forward!$B$4 -> 21870000 | E22: =MoneyMarket!$B$11 -> 23367342 | F22: =MAX(B22,K_PUT)*FC_AMT+FV_PREM_PUT -> 23580094 | G22: =D22-C22 -> -2104080 | H22: =E22-C22 -> -606737.84 | I22: =F22-C22 -> -393985.58 | J22: =IF(AND(D22>=E22,D22>=F22),"Forward",IF(E22>=F22,"Money Market","Put Option")) -> Put Option
A23: 5 | B23: =S0_in*(1+A23*STEP_FRAC) -> 1.21023 | C23: =B23*FC_AMT -> 24204600 | D23: =Forward!$B$4 -> 21870000 | E23: =MoneyMarket!$B$11 -> 23367342 | F23: =MAX(B23,K_PUT)*FC_AMT+FV_PREM_PUT -> 23810614 | G23: =D23-C23 -> -2334600 | H23: =E23-C23 -> -837257.84 | I23: =F23-C23 -> -393985.58 | J23: =IF(AND(D23>=E23,D23>=F23),"Forward",IF(E23>=F23,"Money Market","Put Option")) -> Put Option

Sheet Notes
A1: Notes & Assumptions
A3: Quote convention: all rates expressed as USD per EUR. A higher quote means EUR appreciation.
A4: Horizon: single-maturity model; T_DAYS = 365.
A5: Day-count basis: BASIS = 360 (ACT/360), applied to both USD and EUR legs, matching the
A6: Stage 2 assignment's explicit worked formula (R_FC × T_DAYS/360, R_USD × T_DAYS/360).
A7: Parity: F0_in is course-assigned (Scenario 4), not derived from S0_in/R_USD/R_FC. The
A8: Money Market tab's parity check is therefore expected to show a gap at this stage — it
A9: becomes a closable, live check only once Stage 4 replaces all four inputs with mutually
A10: consistent market data.
A11: Option premium: paid upfront in USD, quoted per 1 unit of EUR (no contract multiplier).
A12: Carried forward at R_USD to FV_PREM_PUT / FV_PREM_CALL.
A13: Counterparty / credit risk: excluded.
... A23: F0_in, PREM_PUT, PREM_CALL: course-assigned, Scenario 4 (Aerospace Manufacturer)
